TOPSIS.py
TOPSIS_Apurv_101803594-1.0.0.dist-info/LICENSE.txt
TOPSIS_Apurv_101803594-1.0.0.dist-info/METADATA
TOPSIS_Apurv_101803594-1.0.0.dist-info/WHEEL
TOPSIS_Apurv_101803594-1.0.0.dist-info/top_level.txt
TOPSIS_Apurv_101803594-1.0.0.dist-info/RECORD
