Metadata-Version: 2.1
Name: TOPSIS-Apurv-101803594
Version: 1.0.0
Summary: TOPSIS Implementation
Home-page: https://github.com/
Author: Apurv Madaan
Author-email: madaanapurv@gmail.com
License: UNKNOWN
Platform: UNKNOWN
Classifier: Programming Language :: Python :: 3
Classifier: Programming Language :: Python :: 3.1
Classifier: Programming Language :: Python :: 3.2
Classifier: Programming Language :: Python :: 3.3
Classifier: Programming Language :: Python :: 3.4
Classifier: Programming Language :: Python :: 3.5
Classifier: Programming Language :: Python :: 3.6
Classifier: Programming Language :: Python :: 3.7
Classifier: Programming Language :: Python :: 3.8
Classifier: License :: OSI Approved :: MIT License
Classifier: Operating System :: OS Independent
Requires-Dist: numpy (>=1.18.1)
Requires-Dist: pandas (>=1.0.5)
Provides-Extra: dev
Requires-Dist: pytest (>=3.7) ; extra == 'dev'
